{
  "/(blank-layout-pages)/login/page": "app/(blank-layout-pages)/login/page.js",
  "/(dashboard)/FindSalon/page": "app/(dashboard)/FindSalon/page.js",
  "/(dashboard)/about/our-story/page": "app/(dashboard)/about/our-story/page.js",
  "/(dashboard)/about/press/page": "app/(dashboard)/about/press/page.js",
  "/(dashboard)/book/page": "app/(dashboard)/book/page.js",
  "/(dashboard)/home/page": "app/(dashboard)/home/page.js",
  "/(dashboard)/legal/cookies/page": "app/(dashboard)/legal/cookies/page.js",
  "/(dashboard)/legal/privacy/page": "app/(dashboard)/legal/privacy/page.js",
  "/(dashboard)/legal/terms/page": "app/(dashboard)/legal/terms/page.js",
  "/(dashboard)/opportunity/investors/page": "app/(dashboard)/opportunity/investors/page.js",
  "/(dashboard)/opportunity/partnerships/page": "app/(dashboard)/opportunity/partnerships/page.js",
  "/(dashboard)/page": "app/(dashboard)/page.js",
  "/(dashboard)/products/latitude/page": "app/(dashboard)/products/latitude/page.js",
  "/(dashboard)/products/manage/[categorySlug]/page": "app/(dashboard)/products/manage/[categorySlug]/page.js",
  "/(dashboard)/products/manage/add/page": "app/(dashboard)/products/manage/add/page.js",
  "/(dashboard)/products/manage/details/[id]/page": "app/(dashboard)/products/manage/details/[id]/page.js",
  "/(dashboard)/products/manage/edit/[id]/page": "app/(dashboard)/products/manage/edit/[id]/page.js",
  "/(dashboard)/products/other/page": "app/(dashboard)/products/other/page.js",
  "/(dashboard)/products/overview/page": "app/(dashboard)/products/overview/page.js",
  "/(dashboard)/products/solution/page": "app/(dashboard)/products/solution/page.js",
  "/(dashboard)/products/tea-tree-solutions/CareProducts/page": "app/(dashboard)/products/tea-tree-solutions/CareProducts/page.js",
  "/(dashboard)/products/tea-tree-solutions/page": "app/(dashboard)/products/tea-tree-solutions/page.js",
  "/(dashboard)/promotions/college-football-playoff/page": "app/(dashboard)/promotions/college-football-playoff/page.js",
  "/(dashboard)/promotions/haircare-sale/page": "app/(dashboard)/promotions/haircare-sale/page.js",
  "/(dashboard)/promotions/ncaa/page": "app/(dashboard)/promotions/ncaa/page.js",
  "/(dashboard)/promotions/nhl/page": "app/(dashboard)/promotions/nhl/page.js",
  "/(dashboard)/promotions/overview/page": "app/(dashboard)/promotions/overview/page.js",
  "/(dashboard)/promotions/senior-discounts/page": "app/(dashboard)/promotions/senior-discounts/page.js",
  "/(dashboard)/services/additional/page": "app/(dashboard)/services/additional/page.js",
  "/(dashboard)/services/blog/[id]/page": "app/(dashboard)/services/blog/[id]/page.js",
  "/(dashboard)/services/blog/new/page": "app/(dashboard)/services/blog/new/page.js",
  "/(dashboard)/services/blog/page": "app/(dashboard)/services/blog/page.js",
  "/(dashboard)/services/check-in/page": "app/(dashboard)/services/check-in/page.js",
  "/(dashboard)/services/clip-notes/page": "app/(dashboard)/services/clip-notes/page.js",
  "/(dashboard)/services/kids/page": "app/(dashboard)/services/kids/page.js",
  "/(dashboard)/services/lookbook/page": "app/(dashboard)/services/lookbook/page.js",
  "/(dashboard)/services/men/page": "app/(dashboard)/services/men/page.js",
  "/(dashboard)/services/overview/page": "app/(dashboard)/services/overview/page.js",
  "/(dashboard)/services/seniors/page": "app/(dashboard)/services/seniors/page.js",
  "/(dashboard)/services/women/page": "app/(dashboard)/services/women/page.js",
  "/(dashboard)/support/contact/page": "app/(dashboard)/support/contact/page.js",
  "/(dashboard)/support/faqs/page": "app/(dashboard)/support/faqs/page.js",
  "/(dashboard)/support/help/page": "app/(dashboard)/support/help/page.js",
  "/[...not-found]/page": "app/[...not-found]/page.js",
  "/_global-error/page": "app/_global-error/page.js",
  "/_not-found/page": "app/_not-found/page.js",
  "/api/blog/[id]/route": "app/api/blog/[id]/route.js",
  "/api/blog/route": "app/api/blog/route.js",
  "/api/cards/route": "app/api/cards/route.js",
  "/api/categories/[id]/route": "app/api/categories/[id]/route.js",
  "/api/categories/route": "app/api/categories/route.js",
  "/api/hairstyles/[id]/route": "app/api/hairstyles/[id]/route.js",
  "/api/hairstyles/route": "app/api/hairstyles/route.js",
  "/api/products/[id]/route": "app/api/products/[id]/route.js",
  "/api/products/route": "app/api/products/route.js",
  "/api/queue/route": "app/api/queue/route.js",
  "/api/upload/products/route": "app/api/upload/products/route.js",
  "/api/upload/route": "app/api/upload/route.js",
  "/blog/[slug]/page": "app/blog/[slug]/page.js",
  "/blog/category/[category]/page": "app/blog/category/[category]/page.js",
  "/blog/page": "app/blog/page.js",
  "/hairstyles/[id]/page": "app/hairstyles/[id]/page.js",
  "/hairstyles/add/page": "app/hairstyles/add/page.js",
  "/hairstyles/page": "app/hairstyles/page.js",
  "/salons-map/page": "app/salons-map/page.js"
}